{
  "sandra": {
    "name": "Sandra",
    "light": {
      "primary": "#F0C1DA",
      "secondary": "#EBA7CB",
      "background": "#F7F5F6",
      "color": "#541136"
    },
    "dark": {
      "color": "#C18BA8",
      "primary": "#521636",
      "secondary": "#320F22",
      "background": "#0F0B0D"
    }
  },
  "josephine": {
    "name": "Joséphine",
    "light": {
      "primary": "#CFCFE2",
      "secondary": "#B9B9D6",
      "background": "#F4F4F8",
      "color": "#262640"
    },
    "dark": {
      "color": "#9B9BB1",
      "primary": "#262640",
      "secondary": "#181828",
      "background": "#0F0B0D"
    }
  },
  "fabrizio": {
    "name": "Fabrizio",
    "light": {
      "primary": "#B8CFFB",
      "secondary": "#9CBAFB",
      "background": "#F8EEFE",
      "color": "#042A63"
    },
    "dark": {
      "primary": "#0E2662",
      "secondary": "#0D153D",
      "background": "#0F0018",
      "color": "#829CCE"
    }
  },
  "florence": {
    "name": "Florence",
    "light": {
      "primary": "#D6F8EA",
      "secondary": "#ABECCA",
      "background": "#F6F6F6",
      "color": "#105735"
    },
    "dark": {
      "color": "#8AC4A8",
      "primary": "#185336",
      "secondary": "#12492E",
      "background": "#0C0D0C"
    }
  },
  "nanny": {
    "name": "Nanny",
    "light": {
      "primary": "#E6E9E8",
      "secondary": "#D9DBD9",
      "background": "#F6F6F6",
      "color": "#313531"
    },
    "dark": {
      "color": "#ACADAC",
      "primary": "#303531",
      "secondary": "#292D29",
      "background": "#0A0B0A"
    }
  },
  "dharma": {
    "name": "Dharma",
    "light": {
      "primary": "#FDE8CD",
      "secondary": "#FACE9B",
      "background": "#F7F6F5",
      "color": "#643A02"
    },
    "dark": {
      "color": "#B6AFA5",
      "primary": "#7B4709",
      "secondary": "#533105",
      "background": "#0F0D0C"
    }
  },
  "hubert": {
    "name": "Hubert",
    "light": {
      "primary": "#EAADC4",
      "secondary": "#EAA8BE",
      "background": "#FCF0F4",
      "color": "#50152B"
    },
    "dark": {
      "color": "#C08C9E",
      "primary": "#50152B",
      "secondary": "#461124",
      "background": "#14050A"
    }
  },
  "slate": {
    "name": "Slate",
    "light": {
      "primary": "#E1E7EF",
      "secondary": "#C1CCDA",
      "background": "#EEF6FE",
      "color": "#0E1729"
    },
    "dark": {
      "color": "#B5BBC5",
      "primary": "#313F52",
      "secondary": "#182333",
      "background": "#010D18"
    }
  },
  "zinc": {
    "name": "Zinc",
    "light": {
      "primary": "#CBCACE",
      "secondary": "#CBCBCF",
      "background": "#F6F6F6",
      "color": "#262729"
    },
    "dark": {
      "color": "#B9B9BC",
      "primary": "#2B2B2F",
      "secondary": "#1A1A1C",
      "background": "#0D0D0D"
    }
  },
  "indigo": {
    "name": "Indigo",
    "light": {
      "primary": "#D2DBFF",
      "secondary": "#B5BEFC",
      "background": "#EEF6FE",
      "color": "#0E1729"
    },
    "dark": {
      "color": "#B5BBC5",
      "primary": "#313F52",
      "secondary": "#182333",
      "background": "#010D18"
    }
  },
  "fuchsia": {
    "name": "Fuchsia",
    "light": {
      "primary": "#FFD2E3",
      "secondary": "#FFB5CB",
      "background": "#FFEDF5",
      "color": "#7F1F4F"
    },
    "dark": {
      "color": "#D09FA9",
      "primary": "#7F1F4F",
      "secondary": "#5F1C5F",
      "background": "#190619"
    }
  },
  "teal": {
    "name": "Teal",
    "light": {
      "primary": "#D2FFEB",
      "secondary": "#B5FFD1",
      "background": "#EDFFF5",
      "color": "#1F7F5F"
    },
    "dark": {
      "color": "#9FD0B9",
      "primary": "#1F7F5F",
      "secondary": "#1C5F4B",
      "background": "#061906"
    }
  },
  "blue": {
    "name": "Blue",
    "light": {
      "primary": "#D2F3FF",
      "secondary": "#B5E6FF",
      "background": "#EDFDFF",
      "color": "#1F6F9F"
    },
    "dark": {
      "color": "#9FC0D0",
      "primary": "#1F6F9F",
      "secondary": "#1C5F7B",
      "background": "#061919"
    }
  },
  "violet": {
    "name": "Violet",
    "light": {
      "primary": "#D2DBFF",
      "secondary": "#B5BEFC",
      "background": "#EDF1FF",
      "color": "#3730A3"
    },
    "dark": {
      "color": "#9FA9D0",
      "primary": "#262484",
      "secondary": "#1C1B5F",
      "background": "#000619"
    }
  },
  "green": {
    "name": "Green",
    "light": {
      "primary": "#D2FFD2",
      "secondary": "#B5FFB5",
      "background": "#EDFFED",
      "color": "#1F7F1F"
    },
    "dark": {
      "color": "#9FD09F",
      "primary": "#1F7F1F",
      "secondary": "#1C5F1C",
      "background": "#061906"
    }
  },
  "orange": {
    "name": "Orange",
    "light": {
      "primary": "#FFD2D2",
      "secondary": "#FFB5B5",
      "background": "#FFEEEE",
      "color": "#7F1F1F"
    },
    "dark": {
      "color": "#D09F9F",
      "primary": "#7F1F1F",
      "secondary": "#5F1C1C",
      "background": "#190606"
    }
  },
  "red": {
    "name": "Red",
    "light": {
      "primary": "#FFD2E3",
      "secondary": "#FFB5CB",
      "background": "#FFEDF5",
      "color": "#7F1F4F"
    },
    "dark": {
      "color": "#D09FA9",
      "primary": "#7F1F4F",
      "secondary": "#5F1C5F",
      "background": "#190619"
    }
  },
  "pink": {
    "name": "Pink",
    "light": {
      "primary": "#FFD2F3",
      "secondary": "#FFB5E6",
      "background": "#FFEDFD",
      "color": "#7F1F6F"
    },
    "dark": {
      "color": "#D09FC0",
      "primary": "#7F1F6F",
      "secondary": "#5F1C5F",
      "background": "#190619"
    }
  },
  "lime": {
    "name": "Lime",
    "light": {
      "primary": "#E3FFD2",
      "secondary": "#CBFFB5",
      "background": "#F5FFED",
      "color": "#4F7F1F"
    },
    "dark": {
      "color": "#A9D09F",
      "primary": "#4F7F1F",
      "secondary": "#3C5F1C",
      "background": "#0F1906"
    }
  },
  "amber": {
    "name": "Amber",
    "light": {
      "primary": "#FFFDD2",
      "secondary": "#FFFBB5",
      "background": "#FFFFED",
      "color": "#7F7F1F"
    },
    "dark": {
      "color": "#D0D09F",
      "primary": "#7F7F1F",
      "secondary": "#5F5F1C",
      "background": "#191906"
    }
  },
  "rose": {
    "name": "Rose",
    "light": {
      "primary": "#FFD2D2",
      "secondary": "#FFB5B5",
      "background": "#FFEEEE",
      "color": "#7F1F1F"
    },
    "dark": {
      "color": "#D09F9F",
      "primary": "#7F1F1F",
      "secondary": "#5F1C1C",
      "background": "#190606"
    }
  },
  "emerald": {
    "name": "Emerald",
    "light": {
      "primary": "#D2FFD2",
      "secondary": "#B5FFB5",
      "background": "#EDFFED",
      "color": "#1F7F1F"
    },
    "dark": {
      "color": "#9FD09F",
      "primary": "#1F7F1F",
      "secondary": "#1C5F1C",
      "background": "#061906"
    }
  },
  "cyan": {
    "name": "Cyan",
    "light": {
      "primary": "#D2F3FF",
      "secondary": "#B5E6FF",
      "background": "#EDFDFF",
      "color": "#1F6F9F"
    },
    "dark": {
      "color": "#9FC0D0",
      "primary": "#1F6F9F",
      "secondary": "#1C5F7B",
      "background": "#061919"
    }
  },

  "lavender": {
    "name": "Lavender",
    "light": {
      "primary": "#E6E6FA",
      "secondary": "#D8BFD8",
      "background": "#F8F8FF",
      "color": "#483D8B"
    },
    "dark": {
      "primary": "#483D8B",
      "secondary": "#4B0082",
      "background": "#191970",
      "color": "#D8BFD8"
    }
  },
  "corail": {
    "name": "Corail",
    "light": {
      "primary": "#FFA07A",
      "secondary": "#FF6347",
      "background": "#FFE4E1",
      "color": "#CD5C5C"
    },
    "dark": {
      "primary": "#CD5C5C",
      "secondary": "#8B0000",
      "background": "#2F4F4F",
      "color": "#FF6347"
    }
  },
  "mint": {
    "name": "Mint",
    "light": {
      "primary": "#98FF98",
      "secondary": "#BDFCC9",
      "background": "#F5FFFA",
      "color": "#3EB489"
    },
    "dark": {
      "primary": "#3EB489",
      "secondary": "#2E8B57",
      "background": "#2F4F4F",
      "color": "#BDFCC9"
    }
  },
  "ocean": {
    "name": "Ocean",
    "light": {
      "primary": "#87CEFA",
      "secondary": "#1E90FF",
      "background": "#F0F8FF",
      "color": "#4682B4"
    },
    "dark": {
      "primary": "#4682B4",
      "secondary": "#000080",
      "background": "#191970",
      "color": "#1E90FF"
    }
  },
  "sunset": {
    "name": "Sunset",
    "light": {
      "primary": "#FF7F50",
      "secondary": "#FF6347",
      "background": "#FFE4E1",
      "color": "#CD5C5C"
    },
    "dark": {
      "primary": "#CD5C5C",
      "secondary": "#8B0000",
      "background": "#2F4F4F",
      "color": "#FF6347"
    }
  },
  "forest": {
    "name": "Forest",
    "light": {
      "primary": "#32CD32",
      "secondary": "#32CD32",
      "background": "#F0FFF0",
      "color": "#006400"
    },
    "dark": {
      "primary": "#006400",
      "secondary": "#2E8B57",
      "background": "#2F4F4F",
      "color": "#32CD32"
    }
  },
  "sunrise": {
    "name": "Sunrise",
    "light": {
      "primary": "#FFDDC1",
      "secondary": "#FFAB91",
      "background": "#FFF3E0",
      "color": "#BF360C"
    },
    "dark": {
      "primary": "#BF360C",
      "secondary": "#D84315",
      "background": "#3E2723",
      "color": "#FFAB91"
    }
  },
  "twilight": {
    "name": "Twilight",
    "light": {
      "primary": "#D1C4E9",
      "secondary": "#B39DDB",
      "background": "#EDE7F6",
      "color": "#311B92"
    },
    "dark": {
      "primary": "#311B92",
      "secondary": "#512DA8",
      "background": "#1A237E",
      "color": "#B39DDB"
    }
  },
  "pastel-dream": {
    "name": "Pastel",
    "light": {
      "primary": "#ADD8E6",
      "secondary": "#FFB6C1",
      "background": "#FFF0F5",
      "color": "#4682B4"
    },
    "dark": {
      "primary": "#4682B4",
      "secondary": "#FF69B4",
      "background": "#2F4F4F",
      "color": "#FFB6C1"
    }
  },
  "tropical-breeze": {
    "name": "Tropical",
    "light": {
      "primary": "#00FA9A",
      "secondary": "#FFD700",
      "background": "#F0FFF0",
      "color": "#006400"
    },
    "dark": {
      "primary": "#006400",
      "secondary": "#FF8C00",
      "background": "#2F4F4F",
      "color": "#FFD700"
    }
  },
  "autumn-glow": {
    "name": "Autumn Glow",
    "light": {
      "primary": "#FF8C00",
      "secondary": "#8B0000",
      "background": "#FFF5EE",
      "color": "#8B4513"
    },
    "dark": {
      "primary": "#8B4513",
      "secondary": "#FF4500",
      "background": "#2F4F4F",
      "color": "#FF8C00"
    }
  },
  "ocean-wave": {
    "name": "Ocean Wave",
    "light": {
      "primary": "#00BFFF",
      "secondary": "#20B2AA",
      "background": "#E0FFFF",
      "color": "#000080"
    },
    "dark": {
      "primary": "#000080",
      "secondary": "#2E8B57",
      "background": "#2F4F4F",
      "color": "#00BFFF"
    }
  },
  "forest-whisper": {
    "name": "Forest Whisper",
    "light": {
      "primary": "#32CD32",
      "secondary": "#FFD700",
      "background": "#F0FFF0",
      "color": "#006400"
    },
    "dark": {
      "primary": "#006400",
      "secondary": "#8B4513",
      "background": "#2F4F4F",
      "color": "#FFD700"
    }
  },
  "midnight-shadow": {
    "name": "Midnight Shadow",
    "light": {
      "primary": "#1C1C1C",
      "secondary": "#ADD8E6",
      "background": "#F5F5F5",
      "color": "#000080"
    },
    "dark": {
      "primary": "#000080",
      "secondary": "#1C1C1C",
      "background": "#2F4F4F",
      "color": "#ADD8E6"
    }
  },
  "charcoal-blush": {
    "name": "Charcoal Blush",
    "light": {
      "primary": "#1C1C1C",
      "secondary": "#FFB6C1",
      "background": "#FFF0F5",
      "color": "#8B0000"
    },
    "dark": {
      "primary": "#8B0000",
      "secondary": "#1C1C1C",
      "background": "#2F4F4F",
      "color": "#FFB6C1"
    }
  }
}
